malevich/__init__.py
malevich/_analytics/__init__.py
malevich/_analytics/decorators/__init__.py
malevich/_analytics/decorators/call_file.py
malevich/_analytics/manager.py
malevich/_analytics/models/__init__.py
malevich/_analytics/models/actions.py
malevich/_analytics/utils.py
malevich/_artifacts/__init__.py
malevich/_artifacts/model.py
malevich/_ast.py
malevich/_autoflow/__init__.py
malevich/_autoflow/flow.py
malevich/_autoflow/function.py
malevich/_autoflow/link.py
malevich/_autoflow/tracer.py
malevich/_autoflow/tree.py
malevich/_cli/__init__.py
malevich/_cli/ci.py
malevich/_cli/core/app.py
malevich/_cli/core/assets.py
malevich/_cli/core/endpoints.py
malevich/_cli/core/limits.py
malevich/_cli/dev/__init__.py
malevich/_cli/dev/dev.py
malevich/_cli/flow.py
malevich/_cli/init.py
malevich/_cli/install.py
malevich/_cli/list.py
malevich/_cli/manifest.py
malevich/_cli/misc/__init__.py
malevich/_cli/misc/make.py
malevich/_cli/misc/manifest_to_env.py
malevich/_cli/new.py
malevich/_cli/prefs.py
malevich/_cli/remove.py
malevich/_cli/restore.py
malevich/_cli/space/init.py
malevich/_cli/space/login.py
malevich/_cli/space/upload.py
malevich/_cli/space/whoami.py
malevich/_cli/use.py
malevich/_core/__init__.py
malevich/_core/ops.py
malevich/_core/refs/__init__.py
malevich/_core/refs/artifact.py
malevich/_core/refs/asset.py
malevich/_core/refs/base.py
malevich/_core/refs/collection.py
malevich/_core/refs/config.py
malevich/_core/refs/pipeline.py
malevich/_core/scan.py
malevich/_core/service/__init__.py
malevich/_core/service/asset.py
malevich/_core/service/base.py
malevich/_core/service/collection.py
malevich/_core/service/configuration.py
malevich/_core/service/document.py
malevich/_core/service/pipeline.py
malevich/_core/service/runs.py
malevich/_core/service/service.py
malevich/_db/__init__.py
malevich/_db/control/__init__.py
malevich/_db/control/read.py
malevich/_db/control/write.py
malevich/_db/functions/__init__.py
malevich/_db/functions/credentials.py
malevich-0.4.1.dist-info/LICENSE
malevich-0.4.1.dist-info/METADATA
malevich-0.4.1.dist-info/WHEEL
malevich-0.4.1.dist-info/entry_points.txt
malevich-0.4.1.dist-info/RECORD
