Metadata-Version: 2.1
Name: malevich
Version: 0.4.1
Summary: 
Author: Aleksandr Lobanov
Author-email: aleksandr.lobanov.official@gmail.com
Requires-Python: >=3.10,<3.11
Classifier: Programming Language :: Python :: 3
Classifier: Programming Language :: Python :: 3.10
Requires-Dist: aiohttp (>=3.10.10,<4.0.0)
Requires-Dist: astor (>=0.8.1,<0.9.0)
Requires-Dist: asyncio (>=3.4.3,<4.0.0)
Requires-Dist: boto3 (>=1.35.49,<2.0.0)
Requires-Dist: botocore (>=1.35.49,<2.0.0)
Requires-Dist: datamodel-code-generator (>=0.26.2,<0.27.0)
Requires-Dist: deepdiff (>=8.0.1,<9.0.0)
Requires-Dist: deprecated (>=1.2.14,<2.0.0)
Requires-Dist: dill (>=0.3.9,<0.4.0)
Requires-Dist: duckdb (>=1.1.2,<2.0.0)
Requires-Dist: duckdb-engine (>=0.13.4,<0.14.0)
Requires-Dist: gitpython (>=3.1.43,<4.0.0)
Requires-Dist: humanfriendly (>=10.0,<11.0)
Requires-Dist: jsonpickle (>=3.3.0,<4.0.0)
Requires-Dist: kafka-python (>=2.0.2,<3.0.0)
Requires-Dist: malevich-app (>=0.2.12,<0.3.0)
Requires-Dist: malevich-coretools (>=0.3.20)
Requires-Dist: malevich-space (>=0.4.27)
Requires-Dist: pandas (>=2.2.3,<3.0.0)
Requires-Dist: pydantic (>=2.0.0)
Requires-Dist: pydantic-yaml (>=1.3.0,<2.0.0)
Requires-Dist: pygithub (>=2.4.0,<3.0.0)
Requires-Dist: python-dotenv (>=1.0.1,<2.0.0)
Requires-Dist: randomname (>=0.2.1,<0.3.0)
Requires-Dist: ruff (>=0.7.1,<0.8.0)
Requires-Dist: typer[all] (>=0.9.0)
